{
  "dictionary": {
    "মুখস্ত করা": {"meaning": "おぼえます", "category": "verb", "dateAdded": "2025-06-24T00:00:00.000Z"},
    "ভুলে যাওয়া": {"meaning": "わすれます", "category": "verb", "dateAdded": "2025-06-24T00:00:00.000Z"},
    "হারিয়ে ফেলা": {"meaning": "なくします", "category": "verb", "dateAdded": "2025-06-24T00:00:00.000Z"},
    "জমা দেওয়া (রিপোর্ট)": {"meaning": "だします", "category": "verb", "dateAdded": "2025-06-24T00:00:00.000Z"},
    "পরিশোধ করা": {"meaning": "はらいます", "category": "verb", "dateAdded": "2025-06-24T00:00:00.000Z"},
    "ফেরত দেওয়া": {"meaning": "かえします", "category": "verb", "dateAdded": "2025-06-24T00:00:00.000Z"},
    "বাইরে যাওয়া": {"meaning": "でかけます", "category": "verb", "dateAdded": "2025-06-24T00:00:00.000Z"},
    "খোলা (জামা, জুতা)": {"meaning": "ぬぎます", "category": "verb", "dateAdded": "2025-06-24T00:00:00.000Z"},
    "(কিছু) নিয়ে যাওয়া": {"meaning": "もっていきます", "category": "verb", "dateAdded": "2025-06-24T00:00:00.000Z"},
    "(কিছু) নিয়ে আসা": {"meaning": "もってきます", "category": "verb", "dateAdded": "2025-06-24T00:00:00.000Z"},
    "চিন্তা করা": {"meaning": "しんばいします", "category": "verb", "dateAdded": "2025-06-24T00:00:00.000Z"},
    "ওভারটাইম কাজ করা": {"meaning": "ざんぎょうします", "category": "verb", "dateAdded": "2025-06-24T00:00:00.000Z"},
    "ব্যবসায়িক সফরে যাওয়া": {"meaning": "しゅっちょうします", "category": "verb", "dateAdded": "2025-06-24T00:00:00.000Z"},
    "খাওয়া (ওষুধ)": {"meaning": "のみます", "category": "verb", "dateAdded": "2025-06-24T00:00:00.000Z"},
    "প্রবেশ করা (গোসলে)": {"meaning": "はいります", "category": "verb", "dateAdded": "2025-06-24T00:00:00.000Z"},
    "গুরুত্বপূর্ণ": {"meaning": "たいせつ [な]", "category": "adjective", "dateAdded": "2025-06-24T00:00:00.000Z"},
    "ঠিক আছে": {"meaning": "だいじょうぶ [な]", "category": "adjective", "dateAdded": "2025-06-24T00:00:00.000Z"},
    "বিপজ্জনক": {"meaning": "あぶない", "category": "adjective", "dateAdded": "2025-06-24T00:00:00.000Z"},
    "সমস্যা / প্রশ্ন": {"meaning": "もんだい", "category": "noun", "dateAdded": "2025-06-24T00:00:00.000Z"},
    "উত্তর": {"meaning": "こたえ", "category": "noun", "dateAdded": "2025-06-24T00:00:00.000Z"},
    "ধূমপান নিষিদ্ধ": {"meaning": "きんえん", "category": "noun", "dateAdded": "2025-06-24T00:00:00.000Z"},
    "স্বাস্থ্য বীমা কার্ড": {"meaning": "けんこう ほけんしょう", "category": "noun", "dateAdded": "2025-06-24T00:00:00.000Z"},
    "সর্দি": {"meaning": "かぜ", "category": "noun", "dateAdded": "2025-06-24T00:00:00.000Z"},
    "জ্বর": {"meaning": "ねつ", "category": "noun", "dateAdded": "2025-06-24T00:00:00.000Z"},
    "রোগ / অসুখ": {"meaning": "びょうき", "category": "noun", "dateAdded": "2025-06-24T00:00:00.000Z"},
    "ওষুধ": {"meaning": "くすり", "category": "noun", "dateAdded": "2025-06-24T00:00:00.000Z"},
    "গোসল": {"meaning": "おふろ", "category": "noun", "dateAdded": "2025-06-24T00:00:00.000Z"},
    "জ্যাকেট": {"meaning": "うわぎ", "category": "noun", "dateAdded": "2025-06-24T00:00:00.000Z"},
    "অন্তর্বাস": {"meaning": "したぎ", "category": "noun", "dateAdded": "2025-06-24T00:00:00.000Z"},
    "ডাক্তার (সম্মানসূচক)": {"meaning": "せんせい", "category": "noun", "dateAdded": "2025-06-24T00:00:00.000Z"},
    "দুই-তিন দিন": {"meaning": "2、3にち", "category": "noun", "dateAdded": "2025-06-24T00:00:00.000Z"},
    "দুই-তিন ~": {"meaning": "2、3～", "category": "counter", "dateAdded": "2025-06-24T00:00:00.000Z"},
    "~এর মধ্যে": {"meaning": "～までに", "category": "particle", "dateAdded": "2025-06-24T00:00:00.000Z"},
    "অতএব　/　তাই": {"meaning": "ですから", "category": "conjunction", "dateAdded": "2025-06-24T00:00:00.000Z"},
    "কি হয়েছে আপনার?": {"meaning": "どうしましたか", "category": "phrase", "dateAdded": "2025-06-24T00:00:00.000Z"},
    "~তে ব্যথা হচ্ছে": {"meaning": "～が いたいです", "category": "phrase", "dateAdded": "2025-06-24T00:00:00.000Z"},
    "গলা": {"meaning": "のど", "category": "noun", "dateAdded": "2025-06-24T00:00:00.000Z"},
    "ভালো থাকুন (রোগীর জন্য)": {"meaning": "おだいじに", "category": "phrase", "dateAdded": "2025-06-24T00:00:00.000Z"}
  },
  "weakWords": []
}